AUTHORS
INSTALL
LICENSE
MANIFEST.in
README
pyproject.toml
setup.py
MDAnalysisTests/__init__.py
MDAnalysisTests/datafiles.py
MDAnalysisTests/dummy.py
MDAnalysisTests/test_api.py
MDAnalysisTests/util.py
MDAnalysisTests.egg-info/PKG-INFO
MDAnalysisTests.egg-info/SOURCES.txt
MDAnalysisTests.egg-info/dependency_links.txt
MDAnalysisTests.egg-info/not-zip-safe
MDAnalysisTests.egg-info/requires.txt
MDAnalysisTests.egg-info/top_level.txt
MDAnalysisTests/analysis/__init__.py
MDAnalysisTests/analysis/conftest.py
MDAnalysisTests/analysis/test_align.py
MDAnalysisTests/analysis/test_atomicdistances.py
MDAnalysisTests/analysis/test_backends.py
MDAnalysisTests/analysis/test_base.py
MDAnalysisTests/analysis/test_bat.py
MDAnalysisTests/analysis/test_contacts.py
MDAnalysisTests/analysis/test_data.py
MDAnalysisTests/analysis/test_density.py
MDAnalysisTests/analysis/test_dielectric.py
MDAnalysisTests/analysis/test_diffusionmap.py
MDAnalysisTests/analysis/test_dihedrals.py
MDAnalysisTests/analysis/test_distances.py
MDAnalysisTests/analysis/test_dssp.py
MDAnalysisTests/analysis/test_encore.py
MDAnalysisTests/analysis/test_gnm.py
MDAnalysisTests/analysis/test_helix_analysis.py
MDAnalysisTests/analysis/test_hole2.py
MDAnalysisTests/analysis/test_hydrogenbondautocorrel.py
MDAnalysisTests/analysis/test_hydrogenbondautocorrel_deprecated.py
MDAnalysisTests/analysis/test_hydrogenbonds_analysis.py
MDAnalysisTests/analysis/test_leaflet.py
MDAnalysisTests/analysis/test_lineardensity.py
MDAnalysisTests/analysis/test_msd.py
MDAnalysisTests/analysis/test_nucleicacids.py
MDAnalysisTests/analysis/test_nuclinfo.py
MDAnalysisTests/analysis/test_pca.py
MDAnalysisTests/analysis/test_persistencelength.py
MDAnalysisTests/analysis/test_psa.py
MDAnalysisTests/analysis/test_rdf.py
MDAnalysisTests/analysis/test_rdf_s.py
MDAnalysisTests/analysis/test_results.py
MDAnalysisTests/analysis/test_rms.py
MDAnalysisTests/analysis/test_waterdynamics.py
MDAnalysisTests/analysis/test_wbridge.py
MDAnalysisTests/auxiliary/__init__.py
MDAnalysisTests/auxiliary/base.py
MDAnalysisTests/auxiliary/test_core.py
MDAnalysisTests/auxiliary/test_edr.py
MDAnalysisTests/auxiliary/test_xvg.py
MDAnalysisTests/converters/__init__.py
