Metadata-Version: 2.4
Name: MDAnalysisTests
Version: 2.10.0
Summary: MDAnalysis testsuite
Author-email: MDAnalysis <mdanalysis@numfocus.org>
Maintainer-email: MDAnalysis <mdanalysis@numfocus.org>
License: ==========================================================================
Project-URL: Homepage, https://www.mdanalysis.org
Project-URL: Download, https://github.com/MDAnalysis/mdanalysis/releases
Project-URL: Documentation, https://docs.mdanalysis.org/
Project-URL: User Guide, https://userguide.mdanalysis.org/
Project-URL: Issue Tracker, https://github.com/mdanalysis/mdanalysis/issues
Project-URL: Github Discussions, https://github.com/MDAnalysis/mdanalysis/discussions
Project-URL: Discord, https://discord.com/channels/807348386012987462/
Project-URL: Blog, https://www.mdanalysis.org/blog/
Project-URL: Source, https://github.com/mdanalysis/mdanalysis
Classifier: Development Status :: 6 - Mature
Classifier: Environment :: Console
Classifier: Intended Audience :: Science/Research
Classifier: License :: OSI Approved :: GNU Lesser General Public License v3 or later (LGPLv3+)
Classifier: Operating System :: POSIX
Classifier: Operating System :: MacOS :: MacOS X
Classifier: Operating System :: Microsoft :: Windows
Classifier: Programming Language :: Python
Classifier: Programming Language :: Python :: 3
Classifier: Programming Language :: Python :: 3.11
Classifier: Programming Language :: Python :: 3.12
Classifier: Programming Language :: Python :: 3.13
Classifier: Programming Language :: Python :: 3.14
Classifier: Programming Language :: C
Classifier: Topic :: Scientific/Engineering
Classifier: Topic :: Scientific/Engineering :: Bio-Informatics
Classifier: Topic :: Scientific/Engineering :: Chemistry
Classifier: Topic :: Software Development :: Libraries :: Python Modules
Requires-Python: >=3.11
License-File: LICENSE
Requires-Dist: MDAnalysis==2.10.0
Requires-Dist: pytest>=3.3.0
Requires-Dist: hypothesis
Dynamic: license-file
Dynamic: requires-dist
